aiovban/__init__.py
aiovban/enums.py
aiovban/asyncio/__init__.py
aiovban/asyncio/device.py
aiovban/asyncio/protocol.py
aiovban/asyncio/streams.py
aiovban/asyncio/util.py
aiovban/packet/__init__.py
aiovban/packet/body/__init__.py
aiovban/packet/body/service/__init__.py
aiovban/packet/body/service/ping.py
aiovban/packet/body/service/rt_packets.py
aiovban/packet/headers/__init__.py
aiovban/packet/headers/audio.py
aiovban/packet/headers/mapping.py
aiovban/packet/headers/serial.py
aiovban/packet/headers/service.py
aiovban/packet/headers/subprotocol.py
aiovban/packet/headers/test___init__.py
aiovban/packet/headers/text.py
aiovban/util/__init__.py
aiovban/util/synthetics.py
aiovban-0.6.3.dist-info/LICENSE
aiovban-0.6.3.dist-info/METADATA
aiovban-0.6.3.dist-info/WHEEL
aiovban-0.6.3.dist-info/top_level.txt
aiovban-0.6.3.dist-info/RECORD
