Metadata-Version: 2.2
Name: aiovban
Version: 0.6.3
Summary: An asyncio VBAN implementation
Author-email: William Best <wmbest2@gmail.com>
Project-URL: Homepage, https://github.com/wmbest2/aiovban
Project-URL: Issues, https://github.com/wmbest2/aiovban/issues
Classifier: Development Status :: 4 - Beta
Classifier: Programming Language :: Python :: 3
Classifier: Programming Language :: Python :: 3.10
Classifier: Programming Language :: Python :: 3.11
Classifier: Programming Language :: Python :: 3.12
Classifier: Programming Language :: Python :: 3.13
Classifier: License :: OSI Approved :: MIT License
Classifier: Operating System :: OS Independent
Requires-Python: >=3.10
License-File: LICENSE
